[
  {
    "name": "slough",
    "etymology": [
      {
        "name": "slughe, slouh",
        "origin": "Middle English"
      },
      {
        "name": "slough",
        "origin": "Modern English"
      },
      {
        "name": "sloff -s",
        "origin": "Inglish",
        "part-of-speech": [
          "masculine noun"
        ]
      }
    ],
    "sources": [
      "https://www.etymonline.com/word/slough#etymonline_v_48784",
      "https://www.merriam-webster.com/dictionary/slough#dictionary-entry-3",
      "https://www.oed.com/dictionary/slough_n2?tab=factsheet#22295292",
      "https://quod.lib.umich.edu/m/middle-english-dictionary/dictionary/MED40968"
    ]
  },
  {
    "name": "to slough",
    "etymology": [
      {
        "name": "to slough",
        "origin": "Modern English"
      },
      {
        "name": "ta sloffe -s -d -ing",
        "origin": "Inglish",
        "part-of-speech": [
          "verb"
        ]
      }
    ],
    "sources": [
      "https://www.etymonline.com/word/slough#etymonline_v_23698",
      "https://www.merriam-webster.com/dictionary/slough#dictionary-entry-4",
      "https://www.oed.com/dictionary/slough_v2?tab=factsheet#22296134"
    ]
  },
  {
    "name": "slough",
    "etymology": [
      {
        "name": "slog, sloh",
        "origin": "Old English"
      },
      {
        "name": "slough",
        "origin": "Middle English"
      },
      {
        "name": "slao -s",
        "origin": "Inglish",
        "part-of-speech": [
          "masculine noun"
        ]
      }
    ],
    "sources": [
      "https://www.etymonline.com/word/slough#etymonline_v_23697",
      "https://www.merriam-webster.com/dictionary/slough#dictionary-entry-1",
      "https://www.oed.com/dictionary/slough_n1?tab=factsheet#22294300",
      "https://quod.lib.umich.edu/m/middle-english-dictionary/dictionary/MED40967",
      "https://bosworthtoller.com/28055"
    ]
  },
  {
    "name": "to slough",
    "etymology": [
      {
        "name": "to slough",
        "origin": "Modern English"
      },
      {
        "name": "ta slaoe -s -d -ing",
        "origin": "Inglish",
        "part-of-speech": [
          "verb"
        ]
      }
    ],
    "sources": [
      "https://www.merriam-webster.com/dictionary/slough#dictionary-entry-2"
    ]
  }
]