[
  {
    "text": "[",
    "lemma": "[",
    "pos": "X",
    "tag": "XX",
    "is_ent": false,
    "whitespace": ""
  },
  {
    "text": "Enter",
    "lemma": "enter",
    "pos": "VERB",
    "tag": "VB",
    "is_ent": false,
    "whitespace": " "
  },
  {
    "text": "JOCASTA",
    "lemma": "JOCASTA",
    "pos": "PROPN",
    "tag": "NNP",
    "is_ent": true,
    "whitespace": " "
  },
  {
    "text": "from",
    "lemma": "from",
    "pos": "ADP",
    "tag": "IN",
    "is_ent": false,
    "whitespace": " "
  },
  {
    "text": "the",
    "lemma": "the",
    "pos": "DET",
    "tag": "DT",
    "is_ent": false,
    "whitespace": " "
  },
  {
    "text": "palace",
    "lemma": "palace",
    "pos": "NOUN",
    "tag": "NN",
    "is_ent": false,
    "whitespace": ""
  },
  {
    "text": ".",
    "lemma": ".",
    "pos": "PUNCT",
    "tag": ".",
    "is_ent": false,
    "whitespace": ""
  },
  {
    "text": "]",
    "lemma": "]",
    "pos": "X",
    "tag": "XX",
    "is_ent": false,
    "whitespace": ""
  },
  {
    "text": "\n\n",
    "lemma": "\n\n",
    "pos": "SPACE",
    "tag": "_SP",
    "is_ent": false,
    "whitespace": ""
  },
  {
    "text": "JOCASTA",
    "lemma": "JOCASTA",
    "pos": "PROPN",
    "tag": "NNP",
    "is_ent": true,
    "whitespace": ""
  },
  {
    "text": "\n\n",
    "lemma": "\n\n",
    "pos": "SPACE",
    "tag": "_SP",
    "is_ent": false,
    "whitespace": ""
  },
  {
    "text": "You",
    "lemma": "you",
    "pos": "PRON",
    "tag": "PRP",
    "is_ent": false,
    "whitespace": " "
  },
  {
    "text": "foolish",
    "lemma": "foolish",
    "pos": "ADJ",
    "tag": "JJ",
    "is_ent": false,
    "whitespace": " "
  },
  {
    "text": "men",
    "lemma": "man",
    "pos": "NOUN",
    "tag": "NNS",
    "is_ent": false,
    "whitespace": ""
  },
  {
    "text": ",",
    "lemma": ",",
    "pos": "PUNCT",
    "tag": ",",
    "is_ent": false,
    "whitespace": " "
  },
  {
    "text": "why",
    "lemma": "why",
    "pos": "SCONJ",
    "tag": "WRB",
    "is_ent": false,
    "whitespace": " "
  },
  {
    "text": "are",
    "lemma": "be",
    "pos": "AUX",
    "tag": "VBP",
    "is_ent": false,
    "whitespace": " "
  },
  {
    "text": "you",
    "lemma": "you",
    "pos": "PRON",
    "tag": "PRP",
    "is_ent": false,
    "whitespace": " "
  },
  {
    "text": "arguing",
    "lemma": "argue",
    "pos": "VERB",
    "tag": "VBG",
    "is_ent": false,
    "whitespace": ""
  },
  {
    "text": "\n",
    "lemma": "\n",
    "pos": "SPACE",
    "tag": "_SP",
    "is_ent": false,
    "whitespace": ""
  },
  {
    "text": "in",
    "lemma": "in",
    "pos": "ADP",
    "tag": "IN",
    "is_ent": false,
    "whitespace": " "
  },
  {
    "text": "such",
    "lemma": "such",
    "pos": "DET",
    "tag": "PDT",
    "is_ent": false,
    "whitespace": " "
  },
  {
    "text": "a",
    "lemma": "a",
    "pos": "DET",
    "tag": "DT",
    "is_ent": false,
    "whitespace": " "
  },
  {
    "text": "stupid",
    "lemma": "stupid",
    "pos": "ADJ",
    "tag": "JJ",
    "is_ent": false,
    "whitespace": " "
  },
  {
    "text": "way",
    "lemma": "way",
    "pos": "NOUN",
    "tag": "NN",
    "is_ent": false,
    "whitespace": ""
  },
  {
    "text": "?",
    "lemma": "?",
    "pos": "PUNCT",
    "tag": ".",
    "is_ent": false,
    "whitespace": " "
  },
  {
    "text": "With",
    "lemma": "with",
    "pos": "SCONJ",
    "tag": "IN",
    "is_ent": false,
    "whitespace": " "
  },
  {
    "text": "our",
    "lemma": "our",
    "pos": "PRON",
    "tag": "PRP$",
    "is_ent": false,
    "whitespace": " "
  },
  {
    "text": "land",
    "lemma": "land",
    "pos": "NOUN",
    "tag": "NN",
    "is_ent": false,
    "whitespace": " "
  },
  {
    "text": "so",
    "lemma": "so",
    "pos": "ADV",
    "tag": "RB",
    "is_ent": false,
    "whitespace": " "
  },
  {
    "text": "sick",
    "lemma": "sick",
    "pos": "ADJ",
    "tag": "JJ",
    "is_ent": false,
    "whitespace": ""
  },
  {
    "text": ",",
    "lemma": ",",
    "pos": "PUNCT",
    "tag": ",",
    "is_ent": false,
    "whitespace": ""
  },
  {
    "text": "\n",
    "lemma": "\n",
    "pos": "SPACE",
    "tag": "_SP",
    "is_ent": false,
    "whitespace": ""
  },
  {
    "text": "are",
    "lemma": "be",
    "pos": "AUX",
    "tag": "VBP",
    "is_ent": false,
    "whitespace": ""
  },
  {
    "text": "n\u2019t",
    "lemma": "not",
    "pos": "PART",
    "tag": "RB",
    "is_ent": false,
    "whitespace": " "
  },
  {
    "text": "you",
    "lemma": "you",
    "pos": "PRON",
    "tag": "PRP",
    "is_ent": false,
    "whitespace": " "
  },
  {
    "text": "ashamed",
    "lemma": "ashamed",
    "pos": "ADJ",
    "tag": "JJ",
    "is_ent": false,
    "whitespace": " "
  },
  {
    "text": "to",
    "lemma": "to",
    "pos": "PART",
    "tag": "TO",
    "is_ent": false,
    "whitespace": " "
  },
  {
    "text": "start",
    "lemma": "start",
    "pos": "VERB",
    "tag": "VB",
    "is_ent": false,
    "whitespace": " "
  },
  {
    "text": "a",
    "lemma": "a",
    "pos": "DET",
    "tag": "DT",
    "is_ent": false,
    "whitespace": " "
  },
  {
    "text": "private",
    "lemma": "private",
    "pos": "ADJ",
    "tag": "JJ",
    "is_ent": false,
    "whitespace": " "
  },
  {
    "text": "fight",
    "lemma": "fight",
    "pos": "NOUN",
    "tag": "NN",
    "is_ent": false,
    "whitespace": ""
  },
  {
    "text": "?",
    "lemma": "?",
    "pos": "PUNCT",
    "tag": ".",
    "is_ent": false,
    "whitespace": ""
  },
  {
    "text": "\n",
    "lemma": "\n",
    "pos": "SPACE",
    "tag": "_SP",
    "is_ent": false,
    "whitespace": ""
  },
  {
    "text": "You",
    "lemma": "you",
    "pos": "PRON",
    "tag": "PRP",
    "is_ent": false,
    "whitespace": ""
  },
  {
    "text": ",",
    "lemma": ",",
    "pos": "PUNCT",
    "tag": ",",
    "is_ent": false,
    "whitespace": " "
  },
  {
    "text": "Oedipus",
    "lemma": "Oedipus",
    "pos": "PROPN",
    "tag": "NNP",
    "is_ent": true,
    "whitespace": ""
  },
  {
    "text": ",",
    "lemma": ",",
    "pos": "PUNCT",
    "tag": ",",
    "is_ent": false,
    "whitespace": " "
  },
  {
    "text": "go",
    "lemma": "go",
    "pos": "VERB",
    "tag": "VB",
    "is_ent": false,
    "whitespace": " "
  },
  {
    "text": "in",
    "lemma": "in",
    "pos": "ADP",
    "tag": "IN",
    "is_ent": false,
    "whitespace": " "
  },
  {
    "text": "the",
    "lemma": "the",
    "pos": "DET",
    "tag": "DT",
    "is_ent": false,
    "whitespace": " "
  },
  {
    "text": "house",
    "lemma": "house",
    "pos": "NOUN",
    "tag": "NN",
    "is_ent": false,
    "whitespace": ""
  },
  {
    "text": ",",
    "lemma": ",",
    "pos": "PUNCT",
    "tag": ",",
    "is_ent": false,
    "whitespace": " "
  },
  {
    "text": "and",
    "lemma": "and",
    "pos": "CCONJ",
    "tag": "CC",
    "is_ent": false,
    "whitespace": " "
  },
  {
    "text": "you",
    "lemma": "you",
    "pos": "PRON",
    "tag": "PRP",
    "is_ent": false,
    "whitespace": ""
  },
  {
    "text": ",",
    "lemma": ",",
    "pos": "PUNCT",
    "tag": ",",
    "is_ent": false,
    "whitespace": ""
  },
  {
    "text": "\n",
    "lemma": "\n",
    "pos": "SPACE",
    "tag": "_SP",
    "is_ent": false,
    "whitespace": ""
  },
  {
    "text": "Creon",
    "lemma": "Creon",
    "pos": "PROPN",
    "tag": "NNP",
    "is_ent": true,
    "whitespace": ""
  },
  {
    "text": ",",
    "lemma": ",",
    "pos": "PUNCT",
    "tag": ",",
    "is_ent": false,
    "whitespace": " "
  },
  {
    "text": "return",
    "lemma": "return",
    "pos": "VERB",
    "tag": "VBP",
    "is_ent": false,
    "whitespace": " "
  },
  {
    "text": "to",
    "lemma": "to",
    "pos": "ADP",
    "tag": "IN",
    "is_ent": false,
    "whitespace": " "
  },
  {
    "text": "yours",
    "lemma": "yours",
    "pos": "PRON",
    "tag": "PRP",
    "is_ent": false,
    "whitespace": ""
  },
  {
    "text": ".",
    "lemma": ".",
    "pos": "PUNCT",
    "tag": ".",
    "is_ent": false,
    "whitespace": " "
  },
  {
    "text": "Why",
    "lemma": "why",
    "pos": "SCONJ",
    "tag": "WRB",
    "is_ent": false,
    "whitespace": " "
  },
  {
    "text": "inflate",
    "lemma": "inflate",
    "pos": "VERB",
    "tag": "VB",
    "is_ent": false,
    "whitespace": ""
  },
  {
    "text": "\n",
    "lemma": "\n",
    "pos": "SPACE",
    "tag": "_SP",
    "is_ent": false,
    "whitespace": ""
  },
  {
    "text": "a",
    "lemma": "a",
    "pos": "DET",
    "tag": "DT",
    "is_ent": false,
    "whitespace": " "
  },
  {
    "text": "trivial",
    "lemma": "trivial",
    "pos": "ADJ",
    "tag": "JJ",
    "is_ent": false,
    "whitespace": " "
  },
  {
    "text": "matter",
    "lemma": "matter",
    "pos": "NOUN",
    "tag": "NN",
    "is_ent": false,
    "whitespace": " "
  },
  {
    "text": "into",
    "lemma": "into",
    "pos": "ADP",
    "tag": "IN",
    "is_ent": false,
    "whitespace": " "
  },
  {
    "text": "something",
    "lemma": "something",
    "pos": "PRON",
    "tag": "NN",
    "is_ent": false,
    "whitespace": " "
  },
  {
    "text": "huge",
    "lemma": "huge",
    "pos": "ADJ",
    "tag": "JJ",
    "is_ent": false,
    "whitespace": ""
  },
  {
    "text": "?",
    "lemma": "?",
    "pos": "PUNCT",
    "tag": ".",
    "is_ent": false,
    "whitespace": ""
  },
  {
    "text": "\n\n\n",
    "lemma": "\n\n\n",
    "pos": "SPACE",
    "tag": "_SP",
    "is_ent": false,
    "whitespace": ""
  },
  {
    "text": "CREON",
    "lemma": "CREON",
    "pos": "PROPN",
    "tag": "NNP",
    "is_ent": true,
    "whitespace": ""
  },
  {
    "text": "\n\n",
    "lemma": "\n\n",
    "pos": "SPACE",
    "tag": "_SP",
    "is_ent": false,
    "whitespace": ""
  },
  {
    "text": "Sister",
    "lemma": "sister",
    "pos": "NOUN",
    "tag": "NN",
    "is_ent": false,
    "whitespace": ""
  },
  {
    "text": ",",
    "lemma": ",",
    "pos": "PUNCT",
    "tag": ",",
    "is_ent": false,
    "whitespace": " "
  },
  {
    "text": "your",
    "lemma": "your",
    "pos": "PRON",
    "tag": "PRP$",
    "is_ent": false,
    "whitespace": " "
  },
  {
    "text": "husband",
    "lemma": "husband",
    "pos": "NOUN",
    "tag": "NN",
    "is_ent": false,
    "whitespace": " "
  },
  {
    "text": "Oedipus",
    "lemma": "Oedipus",
    "pos": "PROPN",
    "tag": "NNP",
    "is_ent": true,
    "whitespace": " "
  },
  {
    "text": "intends",
    "lemma": "intend",
    "pos": "VERB",
    "tag": "VBZ",
    "is_ent": false,
    "whitespace": ""
  },
  {
    "text": "\n",
    "lemma": "\n",
    "pos": "SPACE",
    "tag": "_SP",
    "is_ent": false,
    "whitespace": ""
  },
  {
    "text": "to",
    "lemma": "to",
    "pos": "PART",
    "tag": "TO",
    "is_ent": false,
    "whitespace": " "
  },
  {
    "text": "punish",
    "lemma": "punish",
    "pos": "VERB",
    "tag": "VB",
    "is_ent": false,
    "whitespace": " "
  },
  {
    "text": "me",
    "lemma": "I",
    "pos": "PRON",
    "tag": "PRP",
    "is_ent": false,
    "whitespace": " "
  },
  {
    "text": "in",
    "lemma": "in",
    "pos": "ADP",
    "tag": "IN",
    "is_ent": false,
    "whitespace": " "
  },
  {
    "text": "one",
    "lemma": "one",
    "pos": "NUM",
    "tag": "CD",
    "is_ent": true,
    "whitespace": " "
  },
  {
    "text": "of",
    "lemma": "of",
    "pos": "ADP",
    "tag": "IN",
    "is_ent": false,
    "whitespace": " "
  },
  {
    "text": "two",
    "lemma": "two",
    "pos": "NUM",
    "tag": "CD",
    "is_ent": true,
    "whitespace": " "
  },
  {
    "text": "dreadful",
    "lemma": "dreadful",
    "pos": "ADJ",
    "tag": "JJ",
    "is_ent": false,
    "whitespace": " "
  },
  {
    "text": "ways",
    "lemma": "way",
    "pos": "NOUN",
    "tag": "NNS",
    "is_ent": false,
    "whitespace": ""
  },
  {
    "text": "\u2014",
    "lemma": "\u2014",
    "pos": "PUNCT",
    "tag": ":",
    "is_ent": false,
    "whitespace": ""
  },
  {
    "text": "\n",
    "lemma": "\n",
    "pos": "SPACE",
    "tag": "_SP",
    "is_ent": false,
    "whitespace": ""
  },
  {
    "text": "to",
    "lemma": "to",
    "pos": "PART",
    "tag": "TO",
    "is_ent": false,
    "whitespace": " "
  },
  {
    "text": "banish",
    "lemma": "banish",
    "pos": "VERB",
    "tag": "VB",
    "is_ent": false,
    "whitespace": " "
  },
  {
    "text": "me",
    "lemma": "I",
    "pos": "PRON",
    "tag": "PRP",
    "is_ent": false,
    "whitespace": " "
  },
  {
    "text": "from",
    "lemma": "from",
    "pos": "ADP",
    "tag": "IN",
    "is_ent": false,
    "whitespace": " "
  },
  {
    "text": "my",
    "lemma": "my",
    "pos": "PRON",
    "tag": "PRP$",
    "is_ent": false,
    "whitespace": " "
  },
  {
    "text": "fathers",
    "lemma": "father",
    "pos": "NOUN",
    "tag": "NNS",
    "is_ent": false,
    "whitespace": ""
  },
  {
    "text": "\u2019",
    "lemma": "\u2019",
    "pos": "PART",
    "tag": "POS",
    "is_ent": false,
    "whitespace": " "
  },
  {
    "text": "country",
    "lemma": "country",
    "pos": "NOUN",
    "tag": "NN",
    "is_ent": false,
    "whitespace": ""
  },
  {
    "text": "\n",
    "lemma": "\n",
    "pos": "SPACE",
    "tag": "_SP",
    "is_ent": false,
    "whitespace": ""
  },
  {
    "text": "or",
    "lemma": "or",
    "pos": "CCONJ",
    "tag": "CC",
    "is_ent": false,
    "whitespace": " "
  },
  {
    "text": "arrest",
    "lemma": "arrest",
    "pos": "VERB",
    "tag": "VB",
    "is_ent": false,
    "whitespace": " "
  },
  {
    "text": "me",
    "lemma": "I",
    "pos": "PRON",
    "tag": "PRP",
    "is_ent": false,
    "whitespace": " "
  },
  {
    "text": "and",
    "lemma": "and",
    "pos": "CCONJ",
    "tag": "CC",
    "is_ent": false,
    "whitespace": " "
  },
  {
    "text": "then",
    "lemma": "then",
    "pos": "ADV",
    "tag": "RB",
    "is_ent": false,
    "whitespace": " "
  },
  {
    "text": "have",
    "lemma": "have",
    "pos": "VERB",
    "tag": "VB",
    "is_ent": false,
    "whitespace": " "
  },
  {
    "text": "me",
    "lemma": "I",
    "pos": "PRON",
    "tag": "PRP",
    "is_ent": false,
    "whitespace": " "
  },
  {
    "text": "killed",
    "lemma": "kill",
    "pos": "VERB",
    "tag": "VBN",
    "is_ent": false,
    "whitespace": ""
  },
  {
    "text": ".",
    "lemma": ".",
    "pos": "PUNCT",
    "tag": ".",
    "is_ent": false,
    "whitespace": ""
  },
  {
    "text": "\n\n\n",
    "lemma": "\n\n\n",
    "pos": "SPACE",
    "tag": "_SP",
    "is_ent": false,
    "whitespace": ""
  },
  {
    "text": "OEDIPUS",
    "lemma": "OEDIPUS",
    "pos": "PROPN",
    "tag": "NNP",
    "is_ent": true,
    "whitespace": ""
  },
  {
    "text": "\n\n",
    "lemma": "\n\n",
    "pos": "SPACE",
    "tag": "_SP",
    "is_ent": false,
    "whitespace": ""
  },
  {
    "text": "That",
    "lemma": "that",
    "pos": "PRON",
    "tag": "DT",
    "is_ent": false,
    "whitespace": ""
  },
  {
    "text": "\u2019s",
    "lemma": "\u2019",
    "pos": "VERB",
    "tag": "VBZ",
    "is_ent": false,
    "whitespace": " "
  },
  {
    "text": "right",
    "lemma": "right",
    "pos": "ADJ",
    "tag": "JJ",
    "is_ent": false,
    "whitespace": ""
  },
  {
    "text": ".",
    "lemma": ".",
    "pos": "PUNCT",
    "tag": ".",
    "is_ent": false,
    "whitespace": ""
  },
  {
    "text": "\n",
    "lemma": "\n",
    "pos": "SPACE",
    "tag": "_SP",
    "is_ent": false,
    "whitespace": ""
  },
  {
    "text": "Lady",
    "lemma": "Lady",
    "pos": "PROPN",
    "tag": "NNP",
    "is_ent": false,
    "whitespace": ""
  },
  {
    "text": ",",
    "lemma": ",",
    "pos": "PUNCT",
    "tag": ",",
    "is_ent": false,
    "whitespace": " "
  },
  {
    "text": "I",
    "lemma": "I",
    "pos": "PRON",
    "tag": "PRP",
    "is_ent": false,
    "whitespace": " "
  },
  {
    "text": "caught",
    "lemma": "catch",
    "pos": "VERB",
    "tag": "VBD",
    "is_ent": false,
    "whitespace": " "
  },
  {
    "text": "him",
    "lemma": "he",
    "pos": "PRON",
    "tag": "PRP",
    "is_ent": false,
    "whitespace": " "
  },
  {
    "text": "committing",
    "lemma": "commit",
    "pos": "VERB",
    "tag": "VBG",
    "is_ent": false,
    "whitespace": " "
  },
  {
    "text": "treason",
    "lemma": "treason",
    "pos": "NOUN",
    "tag": "NN",
    "is_ent": false,
    "whitespace": ""
  },
  {
    "text": ",",
    "lemma": ",",
    "pos": "PUNCT",
    "tag": ",",
    "is_ent": false,
    "whitespace": ""
  },
  {
    "text": "\n",
    "lemma": "\n",
    "pos": "SPACE",
    "tag": "_SP",
    "is_ent": false,
    "whitespace": ""
  },
  {
    "text": "a",
    "lemma": "a",
    "pos": "DET",
    "tag": "DT",
    "is_ent": false,
    "whitespace": " "
  },
  {
    "text": "vicious",
    "lemma": "vicious",
    "pos": "ADJ",
    "tag": "JJ",
    "is_ent": false,
    "whitespace": " "
  },
  {
    "text": "crime",
    "lemma": "crime",
    "pos": "NOUN",
    "tag": "NN",
    "is_ent": false,
    "whitespace": " "
  },
  {
    "text": "against",
    "lemma": "against",
    "pos": "ADP",
    "tag": "IN",
    "is_ent": false,
    "whitespace": " "
  },
  {
    "text": "me",
    "lemma": "I",
    "pos": "PRON",
    "tag": "PRP",
    "is_ent": false,
    "whitespace": " "
  },
  {
    "text": "personally",
    "lemma": "personally",
    "pos": "ADV",
    "tag": "RB",
    "is_ent": false,
    "whitespace": ""
  },
  {
    "text": ".",
    "lemma": ".",
    "pos": "PUNCT",
    "tag": ".",
    "is_ent": false,
    "whitespace": ""
  },
  {
    "text": "\n\n\n",
    "lemma": "\n\n\n",
    "pos": "SPACE",
    "tag": "_SP",
    "is_ent": false,
    "whitespace": ""
  },
  {
    "text": "CREON",
    "lemma": "CREON",
    "pos": "PROPN",
    "tag": "NNP",
    "is_ent": true,
    "whitespace": ""
  },
  {
    "text": "\n\n",
    "lemma": "\n\n",
    "pos": "SPACE",
    "tag": "_SP",
    "is_ent": false,
    "whitespace": ""
  },
  {
    "text": "Let",
    "lemma": "let",
    "pos": "VERB",
    "tag": "VB",
    "is_ent": false,
    "whitespace": " "
  },
  {
    "text": "me",
    "lemma": "I",
    "pos": "PRON",
    "tag": "PRP",
    "is_ent": false,
    "whitespace": " "
  },
  {
    "text": "not",
    "lemma": "not",
    "pos": "PART",
    "tag": "RB",
    "is_ent": false,
    "whitespace": " "
  },
  {
    "text": "prosper",
    "lemma": "prosper",
    "pos": "VERB",
    "tag": "VB",
    "is_ent": false,
    "whitespace": " "
  },
  {
    "text": "but",
    "lemma": "but",
    "pos": "CCONJ",
    "tag": "CC",
    "is_ent": false,
    "whitespace": " "
  },
  {
    "text": "die",
    "lemma": "die",
    "pos": "VERB",
    "tag": "VB",
    "is_ent": false,
    "whitespace": " "
  },
  {
    "text": "a",
    "lemma": "a",
    "pos": "DET",
    "tag": "DT",
    "is_ent": false,
    "whitespace": " "
  },
  {
    "text": "man",
    "lemma": "man",
    "pos": "NOUN",
    "tag": "NN",
    "is_ent": false,
    "whitespace": " "
  },
  {
    "text": "accursed",
    "lemma": "accurse",
    "pos": "VERB",
    "tag": "VBN",
    "is_ent": false,
    "whitespace": ""
  },
  {
    "text": ",",
    "lemma": ",",
    "pos": "PUNCT",
    "tag": ",",
    "is_ent": false,
    "whitespace": ""
  },
  {
    "text": "\n",
    "lemma": "\n",
    "pos": "SPACE",
    "tag": "_SP",
    "is_ent": false,
    "whitespace": ""
  },
  {
    "text": "if",
    "lemma": "if",
    "pos": "SCONJ",
    "tag": "IN",
    "is_ent": false,
    "whitespace": " "
  },
  {
    "text": "I",
    "lemma": "I",
    "pos": "PRON",
    "tag": "PRP",
    "is_ent": false,
    "whitespace": " "
  },
  {
    "text": "have",
    "lemma": "have",
    "pos": "AUX",
    "tag": "VBP",
    "is_ent": false,
    "whitespace": " "
  },
  {
    "text": "done",
    "lemma": "do",
    "pos": "VERB",
    "tag": "VBN",
    "is_ent": false,
    "whitespace": " "
  },
  {
    "text": "what",
    "lemma": "what",
    "pos": "PRON",
    "tag": "WP",
    "is_ent": false,
    "whitespace": " "
  },
  {
    "text": "you",
    "lemma": "you",
    "pos": "PRON",
    "tag": "PRP",
    "is_ent": false,
    "whitespace": " "
  },
  {
    "text": "accuse",
    "lemma": "accuse",
    "pos": "VERB",
    "tag": "VBP",
    "is_ent": false,
    "whitespace": " "
  },
  {
    "text": "me",
    "lemma": "I",
    "pos": "PRON",
    "tag": "PRP",
    "is_ent": false,
    "whitespace": " "
  },
  {
    "text": "of",
    "lemma": "of",
    "pos": "ADP",
    "tag": "IN",
    "is_ent": false,
    "whitespace": ""
  },
  {
    "text": ".",
    "lemma": ".",
    "pos": "PUNCT",
    "tag": ".",
    "is_ent": false,
    "whitespace": ""
  },
  {
    "text": "\n\n\n",
    "lemma": "\n\n\n",
    "pos": "SPACE",
    "tag": "_SP",
    "is_ent": false,
    "whitespace": ""
  },
  {
    "text": "JOCASTA",
    "lemma": "JOCASTA",
    "pos": "PROPN",
    "tag": "NNP",
    "is_ent": true,
    "whitespace": ""
  },
  {
    "text": "\n\n",
    "lemma": "\n\n",
    "pos": "SPACE",
    "tag": "_SP",
    "is_ent": false,
    "whitespace": ""
  },
  {
    "text": "Oedipus",
    "lemma": "Oedipus",
    "pos": "PROPN",
    "tag": "NNP",
    "is_ent": true,
    "whitespace": ""
  },
  {
    "text": ",",
    "lemma": ",",
    "pos": "PUNCT",
    "tag": ",",
    "is_ent": false,
    "whitespace": ""
  },
  {
    "text": "\n",
    "lemma": "\n",
    "pos": "SPACE",
    "tag": "_SP",
    "is_ent": false,
    "whitespace": ""
  },
  {
    "text": "for",
    "lemma": "for",
    "pos": "ADP",
    "tag": "IN",
    "is_ent": false,
    "whitespace": " "
  },
  {
    "text": "the",
    "lemma": "the",
    "pos": "DET",
    "tag": "DT",
    "is_ent": false,
    "whitespace": " "
  },
  {
    "text": "sake",
    "lemma": "sake",
    "pos": "NOUN",
    "tag": "NN",
    "is_ent": false,
    "whitespace": " "
  },
  {
    "text": "of",
    "lemma": "of",
    "pos": "ADP",
    "tag": "IN",
    "is_ent": false,
    "whitespace": " "
  },
  {
    "text": "the",
    "lemma": "the",
    "pos": "DET",
    "tag": "DT",
    "is_ent": false,
    "whitespace": " "
  },
  {
    "text": "gods",
    "lemma": "god",
    "pos": "NOUN",
    "tag": "NNS",
    "is_ent": false,
    "whitespace": ""
  },
  {
    "text": ",",
    "lemma": ",",
    "pos": "PUNCT",
    "tag": ",",
    "is_ent": false,
    "whitespace": " "
  },
  {
    "text": "trust",
    "lemma": "trust",
    "pos": "VERB",
    "tag": "VB",
    "is_ent": false,
    "whitespace": " "
  },
  {
    "text": "him",
    "lemma": "he",
    "pos": "PRON",
    "tag": "PRP",
    "is_ent": false,
    "whitespace": " "
  },
  {
    "text": "in",
    "lemma": "in",
    "pos": "ADP",
    "tag": "IN",
    "is_ent": false,
    "whitespace": " "
  },
  {
    "text": "this",
    "lemma": "this",
    "pos": "PRON",
    "tag": "DT",
    "is_ent": false,
    "whitespace": ""
  },
  {
    "text": ".",
    "lemma": ".",
    "pos": "PUNCT",
    "tag": ".",
    "is_ent": false,
    "whitespace": ""
  },
  {
    "text": "\n",
    "lemma": "\n",
    "pos": "SPACE",
    "tag": "_SP",
    "is_ent": false,
    "whitespace": ""
  },
  {
    "text": "Respect",
    "lemma": "respect",
    "pos": "VERB",
    "tag": "VB",
    "is_ent": false,
    "whitespace": " "
  },
  {
    "text": "that",
    "lemma": "that",
    "pos": "DET",
    "tag": "DT",
    "is_ent": false,
    "whitespace": " "
  },
  {
    "text": "oath",
    "lemma": "oath",
    "pos": "NOUN",
    "tag": "NN",
    "is_ent": false,
    "whitespace": " "
  },
  {
    "text": "he",
    "lemma": "he",
    "pos": "PRON",
    "tag": "PRP",
    "is_ent": false,
    "whitespace": " "
  },
  {
    "text": "made",
    "lemma": "make",
    "pos": "VERB",
    "tag": "VBD",
    "is_ent": false,
    "whitespace": " "
  },
  {
    "text": "before",
    "lemma": "before",
    "pos": "ADP",
    "tag": "IN",
    "is_ent": false,
    "whitespace": " "
  },
  {
    "text": "all",
    "lemma": "all",
    "pos": "DET",
    "tag": "DT",
    "is_ent": false,
    "whitespace": " "
  },
  {
    "text": "heaven",
    "lemma": "heaven",
    "pos": "NOUN",
    "tag": "NN",
    "is_ent": false,
    "whitespace": ""
  },
  {
    "text": "\u2014",
    "lemma": "\u2014",
    "pos": "PUNCT",
    "tag": ":",
    "is_ent": false,
    "whitespace": ""
  },
  {
    "text": "\n",
    "lemma": "\n",
    "pos": "SPACE",
    "tag": "_SP",
    "is_ent": false,
    "whitespace": ""
  },
  {
    "text": "do",
    "lemma": "do",
    "pos": "VERB",
    "tag": "VB",
    "is_ent": false,
    "whitespace": " "
  },
  {
    "text": "it",
    "lemma": "it",
    "pos": "PRON",
    "tag": "PRP",
    "is_ent": false,
    "whitespace": " "
  },
  {
    "text": "for",
    "lemma": "for",
    "pos": "ADP",
    "tag": "IN",
    "is_ent": false,
    "whitespace": " "
  },
  {
    "text": "my",
    "lemma": "my",
    "pos": "PRON",
    "tag": "PRP$",
    "is_ent": false,
    "whitespace": " "
  },
  {
    "text": "sake",
    "lemma": "sake",
    "pos": "NOUN",
    "tag": "NN",
    "is_ent": false,
    "whitespace": " "
  },
  {
    "text": "and",
    "lemma": "and",
    "pos": "CCONJ",
    "tag": "CC",
    "is_ent": false,
    "whitespace": " "
  },
  {
    "text": "for",
    "lemma": "for",
    "pos": "ADP",
    "tag": "IN",
    "is_ent": false,
    "whitespace": " "
  },
  {
    "text": "those",
    "lemma": "those",
    "pos": "PRON",
    "tag": "DT",
    "is_ent": false,
    "whitespace": " "
  },
  {
    "text": "around",
    "lemma": "around",
    "pos": "ADP",
    "tag": "IN",
    "is_ent": false,
    "whitespace": " "
  },
  {
    "text": "you",
    "lemma": "you",
    "pos": "PRON",
    "tag": "PRP",
    "is_ent": false,
    "whitespace": ""
  },
  {
    "text": ".",
    "lemma": ".",
    "pos": "PUNCT",
    "tag": ".",
    "is_ent": false,
    "whitespace": ""
  },
  {
    "text": "\n\n\n",
    "lemma": "\n\n\n",
    "pos": "SPACE",
    "tag": "_SP",
    "is_ent": false,
    "whitespace": ""
  },
  {
    "text": "CHORUS",
    "lemma": "CHORUS",
    "pos": "PROPN",
    "tag": "NNP",
    "is_ent": true,
    "whitespace": " "
  },
  {
    "text": "LEADER",
    "lemma": "LEADER",
    "pos": "PROPN",
    "tag": "NNP",
    "is_ent": true,
    "whitespace": ""
  },
  {
    "text": "\n\n",
    "lemma": "\n\n",
    "pos": "SPACE",
    "tag": "_SP",
    "is_ent": false,
    "whitespace": ""
  },
  {
    "text": "I",
    "lemma": "I",
    "pos": "PRON",
    "tag": "PRP",
    "is_ent": false,
    "whitespace": " "
  },
  {
    "text": "beg",
    "lemma": "beg",
    "pos": "VERB",
    "tag": "VBP",
    "is_ent": false,
    "whitespace": " "
  },
  {
    "text": "you",
    "lemma": "you",
    "pos": "PRON",
    "tag": "PRP",
    "is_ent": false,
    "whitespace": ""
  },
  {
    "text": ",",
    "lemma": ",",
    "pos": "PUNCT",
    "tag": ",",
    "is_ent": false,
    "whitespace": " "
  },
  {
    "text": "my",
    "lemma": "my",
    "pos": "PRON",
    "tag": "PRP$",
    "is_ent": false,
    "whitespace": " "
  },
  {
    "text": "lord",
    "lemma": "lord",
    "pos": "NOUN",
    "tag": "NN",
    "is_ent": false,
    "whitespace": ""
  },
  {
    "text": ",",
    "lemma": ",",
    "pos": "PUNCT",
    "tag": ",",
    "is_ent": false,
    "whitespace": " "
  },
  {
    "text": "consent",
    "lemma": "consent",
    "pos": "VERB",
    "tag": "VB",
    "is_ent": false,
    "whitespace": " "
  },
  {
    "text": "to",
    "lemma": "to",
    "pos": "ADP",
    "tag": "IN",
    "is_ent": false,
    "whitespace": " "
  },
  {
    "text": "this",
    "lemma": "this",
    "pos": "PRON",
    "tag": "DT",
    "is_ent": false,
    "whitespace": ""
  },
  {
    "text": "\u2014",
    "lemma": "\u2014",
    "pos": "PUNCT",
    "tag": ":",
    "is_ent": false,
    "whitespace": ""
  },
  {
    "text": "\n",
    "lemma": "\n",
    "pos": "SPACE",
    "tag": "_SP",
    "is_ent": false,
    "whitespace": ""
  },
  {
    "text": "agree",
    "lemma": "agree",
    "pos": "VERB",
    "tag": "VB",
    "is_ent": false,
    "whitespace": " "
  },
  {
    "text": "with",
    "lemma": "with",
    "pos": "ADP",
    "tag": "IN",
    "is_ent": false,
    "whitespace": " "
  },
  {
    "text": "her",
    "lemma": "she",
    "pos": "PRON",
    "tag": "PRP",
    "is_ent": false,
    "whitespace": ""
  },
  {
    "text": ".",
    "lemma": ".",
    "pos": "PUNCT",
    "tag": ".",
    "is_ent": false,
    "whitespace": " "
  },
  {
    "text": "                          \n",
    "lemma": "                          \n",
    "pos": "SPACE",
    "tag": "_SP",
    "is_ent": false,
    "whitespace": ""
  }
]