[
  {
    "name": "to wind",
    "etymology": [
      {
        "name": "windan",
        "origin": "Old English"
      },
      {
        "name": "winden",
        "origin": "Middle English"
      },
      {
        "name": "to wind",
        "origin": "Modern English"
      },
      {
        "name": "ta ɯînd -s ɯàund -ing (v)",
        "origin": "Inglish"
      }
    ],
    "sources": [
      "https://www.etymonline.com/word/wind#etymonline_v_10774",
      "https://www.merriam-webster.com/dictionary/wind#dictionary-entry-3",
      "https://quod.lib.umich.edu/m/middle-english-dictionary/dictionary/MED52864",
      "https://bosworthtoller.com/35856"
    ]
  },
  {
    "name": "wind",
    "etymology": [
      {
        "name": "wind",
        "origin": "Old English"
      },
      {
        "name": "ɯind -s (n)",
        "origin": "Inglish"
      }
    ],
    "sources": [
      "https://www.etymonline.com/word/wind#etymonline_v_10773",
      "https://www.merriam-webster.com/dictionary/wind#dictionary-entry-1",
      "https://quod.lib.umich.edu/m/middle-english-dictionary/dictionary/MED52851",
      "https://bosworthtoller.com/35851"
    ]
  },
  {
    "name": "to wind",
    "etymology": [
      {
        "name": "to wind",
        "origin": "Modern English"
      },
      {
        "name": "ta ɯinde -s -d -ing (v)",
        "origin": "Inglish"
      }
    ],
    "sources": [
      "https://www.etymonline.com/word/wind#etymonline_v_44481",
      "https://www.etymonline.com/word/wind#etymonline_v_10773",
      "https://www.merriam-webster.com/dictionary/wind#dictionary-entry-2"
    ]
  }
]