[
  {
    "infinitive": "to try",
    "etymology": [
      {
        "name": "trier",
        "origin": "Old French"
      },
      {
        "name": "trien",
        "origin": "Middle English"
      },
      {
        "name": "to try",
        "origin": "Modern English"
      },
      {
        "name": "ta trîe -s -d trîhing",
        "origin": "Inglish",
        "part-of-speech": [
          "verb"
        ],
        "conjugations": {
          "thirdPerson": "ta trîes",
          "pastTense": "ta trîed"
        }
      }
    ],
    "sources": [
      "https://www.etymonline.com/word/try#etymonline_v_17904",
      "https://www.merriam-webster.com/dictionary/try#dictionary-entry-1",
      "https://quod.lib.umich.edu/m/middle-english-dictionary/dictionary/MED47079",
      "https://www.anglo-norman.net/entry/trier",
      "https://www.littre.org/definition/trier"
    ]
  },
  {
    "name": "try",
    "etymology": [
      {
        "name": "try",
        "origin": "Modern English"
      },
      {
        "name": "trîe, trîs",
        "origin": "Inglish",
        "part-of-speech": [
          "noun"
        ],
        "number": "singular"
      }
    ],
    "sources": [
      "https://www.etymonline.com/word/try#etymonline_v_49650",
      "https://www.etymonline.com/word/try#etymonline_v_17904",
      "https://www.merriam-webster.com/dictionary/try#dictionary-entry-2"
    ]
  },
  {
    "name": "trial",
    "etymology": [
      {
        "name": "trial",
        "origin": "Old French"
      },
      {
        "name": "trîal -s",
        "origin": "Inglish",
        "part-of-speech": [
          "noun"
        ],
        "number": "singular"
      }
    ],
    "sources": [
      "https://www.etymonline.com/word/trial#etymonline_v_17799",
      "https://www.merriam-webster.com/dictionary/trial#dictionary-entry-1",
      "https://anglo-norman.net/entry/trial"
    ]
  },
  {
    "infinitive": "to trial",
    "etymology": [
      {
        "name": "to trial",
        "origin": "Modern English"
      },
      {
        "name": "ta trîale -s -d -ing",
        "origin": "Inglish",
        "part-of-speech": [
          "verb"
        ],
        "conjugations": {
          "thirdPerson": "ta trîales",
          "pastTense": "ta trîaled",
          "progressive": "ta trîaling"
        }
      }
    ],
    "sources": [
      "https://www.merriam-webster.com/dictionary/trial#dictionary-entry-3"
    ]
  }
]