[
  {
    "name": "to breed",
    "etymology": [
      {
        "name": "bredan",
        "origin": "Old English"
      },
      {
        "name": "breden",
        "origin": "Middle English"
      },
      {
        "name": "to breed",
        "origin": "Modern English"
      },
      {
        "name": "ta briede -s brèd -iŋ",
        "origin": "Inglish"
      }
    ],
    "sources": [
      "https://www.etymonline.com/word/breed#etymonline_v_17087",
      "https://www.merriam-webster.com/dictionary/breed#dictionary-entry-1",
      "https://quod.lib.umich.edu/m/middle-english-dictionary/dictionary/MED5882",
      "https://bosworthtoller.com/40844"
    ]
  },
  {
    "name": "breed",
    "etymology": [
      {
        "name": "breed",
        "origin": "Modern English"
      },
      {
        "name": "bried -s (n)",
        "origin": "Inglish"
      }
    ],
    "sources": [
      "https://www.etymonline.com/word/breed#etymonline_v_44275",
      "https://www.etymonline.com/word/breed#etymonline_v_17087",
      "https://www.merriam-webster.com/dictionary/breed#dictionary-entry-2"
    ]
  }
]